<?xml version='1.0' encoding='windows-1252'?>
<LANGUAGE><LABEL name="ViewMoreInfo">Scroll Down to view more information.</LABEL>
	<LABEL name="WMPDownloadText">Click Here to download the most current version of Microsoft Media Player</LABEL>
	<LABEL name="ViewMediaPlayer">Press the "Escape" key to return from Full Screen Viewing.</LABEL>
	<LABEL name="RealDownloadText">Click Here to download the most current version of Real Player</LABEL>
	<LABEL name="ViewRealPlayer">Right click the video for viewing options.</LABEL>
	<LABEL name="LoadFlashPlayer">LoadFlashPlayer</LABEL>
	<LABEL name="Preview">COPY URL FOR CUSTOMER PREVIEW</LABEL>
	<LABEL name="Close">Close</LABEL>
	<LABEL name="1X">View Regular Size</LABEL>
	<LABEL name="2X">View Double Size</LABEL>
	<LABEL name="FullX">View Full Screen</LABEL>
</LANGUAGE>
