<?xml version='1.0' encoding='windows-1252'?>
<LANGUAGE><LABEL name="A">Marketing Menu</LABEL>
	<LABEL name="hh">Contact Manager</LABEL>
	<LABEL name="E">Sales Management System</LABEL>
	<LABEL name="a6">Customer Service</LABEL>
	<LABEL name="Y">Lead Ads</LABEL>
	<LABEL name="Z">Lead Capture Pages</LABEL>
	<LABEL name="zz">Presentation Pages</LABEL>
	<LABEL name="lcurly">Personalize Presentation</LABEL>
	<LABEL name="a5">Drip Email Campaigns</LABEL>
	<LABEL name="a3">DO NOT allow access to the Sales Reports</LABEL>
	<LABEL name="a1">Lookup Existing Sales Prospects</LABEL>
	<LABEL name="nn">Productivity Menu</LABEL>
	<LABEL name="ll">Activity Tracker</LABEL>
	<LABEL name="star">Activity Contests</LABEL>
	<LABEL name="pound">Activity Reports</LABEL>
	<LABEL name="lbracket">Performance Statistics</LABEL>
	<LABEL name="ss">Shortcuts</LABEL>
	<LABEL name="H">Goal Management System</LABEL>
	<LABEL name="a2">Personal and Team Calendars</LABEL>
	<LABEL name="a7">Party/Meeting Planner</LABEL>
	<LABEL name="F">Project Management System</LABEL>
	<LABEL name="ff">Secured Projects</LABEL>
	<LABEL name="I">Member Profile</LABEL>
	<LABEL name="ii">Dashboard</LABEL>
	<LABEL name="G">Ability to be Mentored</LABEL>
	<LABEL name="gg">Ability to be a Mentor</LABEL>
	<LABEL name="W">Newsleter Subscriptions</LABEL>
	<LABEL name="oo">Sales Team</LABEL>
	<LABEL name="B">Training Menu</LABEL>
	<LABEL name="K">Training Classes</LABEL>
	<LABEL name="L">Assessments and Certifications</LABEL>
	<LABEL name="a9">DO NOT allow access to new assessments</LABEL>
	<LABEL name="M">Public Course Catalog</LABEL>
	<LABEL name="ww">Finances Menu</LABEL>
	<LABEL name="V">Member Payments</LABEL>
	<LABEL name="jj">Sales Orders</LABEL>
	<LABEL name="rparen">Credits</LABEL>
	<LABEL name="pp">Bonuses</LABEL>
	<LABEL name="xx">Payouts</LABEL>
	<LABEL name="N">Member Sales Summary</LABEL>
	<LABEL name="fslash">Wealth Builder</LABEL>
	<LABEL name="semicolon">Referral Program</LABEL>
	<LABEL name="J">Customer Orders</LABEL>
	<LABEL name="a8">Shopping</LABEL>
	<LABEL name="percent">Autoship</LABEL>
	<LABEL name="aa">Resource Center</LABEL>
	<LABEL name="bb">Custom Success Tracks</LABEL>
	<LABEL name="dd">Custom Upload Documents</LABEL>
	<LABEL name="cc">Custom Email Templates</LABEL>
	<LABEL name="ee">Custom Information Pages</LABEL>
	<LABEL name="rcurly">Publish Newsleters</LABEL>
	<LABEL name="bar">Team Admin Members</LABEL>
	<LABEL name="bslash">Team Admin Options</LABEL>
	<LABEL name="underscore">Team Admin Sales Campaigns</LABEL>
	<LABEL name="plus">Team Admin Lead Pages</LABEL>
	<LABEL name="equal">Team Admin Presentations</LABEL>
	<LABEL name="a4">Team Admin Training</LABEL>
	<LABEL name="a0">Create Contests</LABEL>
	<LABEL name="D">Support Menu</LABEL>
	<LABEL name="U">Pinnacle Tutorials</LABEL>
	<LABEL name="S">The Guide</LABEL>
	<LABEL name="R">Support Document Search Engine</LABEL>
	<LABEL name="T">Pinnacle QA Search Engine</LABEL>
	<LABEL name="mm">Support Tickets</LABEL>
	<LABEL name="C">Communication Menu</LABEL>
	<LABEL name="O">Discussion Boards</LABEL>
	<LABEL name="P">Suggestion Boxes</LABEL>
	<LABEL name="Q">Company Surveys</LABEL>
	<LABEL name="X">Affiliate Management System</LABEL>
	<LABEL name="kk">Allow Duplicate Email Addresses</LABEL>
	<LABEL name="qq">Member Extra Information</LABEL>
	<LABEL name="rr">Prospect Extra Information</LABEL>
	<LABEL name="tt">Member Forms</LABEL>
	<LABEL name="uu">Prospect Forms</LABEL>
	<LABEL name="vv">Member Titles</LABEL>
	<LABEL name="at">Member Messages</LABEL>
	<LABEL name="lparen">Public Social Network Links</LABEL>
	<LABEL name="period">Custom Reports</LABEL>
	<LABEL name="comma">Company Website</LABEL>
	<LABEL name="rbracket">Group Reports</LABEL>
	<LABEL name="yy">DO NOT allow editing of Logon Name</LABEL>
	<LABEL name="exclaim">DO NOT allow access to Login Information</LABEL>
	<LABEL name="dollar">DO NOT allow access to Search Engine</LABEL>
	<LABEL name="colon">DO NOT allow editing of the Member Team</LABEL>
	<LABEL name="caret">DO NOT display default member home page</LABEL>
	<LABEL name="MemberOptions">Member Options</LABEL>
	<LABEL name="Level">Level</LABEL>
	<LABEL name="Update">Update</LABEL>
	<LABEL name="Return">Return</LABEL>
</LANGUAGE>
