<?xml version='1.0' encoding='windows-1252'?>
<LANGUAGE><LABEL name="AuthLog">Logon IP</LABEL>
	<LABEL name="AuthLogs">Logon IPs</LABEL>
	<LABEL name="NewAuthLog">New Logon IP</LABEL>
	<LABEL name="FindAuthLog">Logon IPs</LABEL>
	<LABEL name="AuthLogID">Logon IP</LABEL>
	<LABEL name="AuthUserID">Authorized User ID</LABEL>
	<LABEL name="IP">IP Address</LABEL>
	<LABEL name="LogDate">First Access</LABEL>
	<LABEL name="LastDate">Last Access</LABEL>
	<LABEL name="Total">Total</LABEL>
	<LABEL name="Status">Status</LABEL>
	<LABEL name="Allow">Allowed</LABEL>
	<LABEL name="Disallow">Disallowed</LABEL>
	<LABEL name="Override">Override</LABEL>
</LANGUAGE>
