<?xml version='1.0' encoding='windows-1252'?>
<LANGUAGE><LABEL name="ProjectType">Project Type</LABEL>
	<LABEL name="ProjectTypes">Project Types</LABEL>
	<LABEL name="NewProjectType">Add New Project Type</LABEL>
	<LABEL name="FindProjectType">Project Types</LABEL>
	<LABEL name="ProjectTypeID">Project Type</LABEL>
	<LABEL name="CompanyID">Company #</LABEL>
	<LABEL name="ProjectTypeName">Name</LABEL>
	<LABEL name="Seq">Sequence</LABEL>
	<LABEL name="Help">Help</LABEL>
	<LABEL name="ProjectTypesText">Click the name of the Project Type to edit it.  Select the "Add New Project Type" link in the upper right hand corner of this page.</LABEL>
</LANGUAGE>
