<?xml version='1.0' encoding='windows-1252'?>
<LANGUAGE><LABEL name="Shortcut">Shortcut</LABEL>
	<LABEL name="NewShortcut">New Shortcut</LABEL>
	<LABEL name="FindShortcut">Find Shortcut</LABEL>
	<LABEL name="ShortcutID">Shortcut</LABEL>
	<LABEL name="AuthUserID">AuthUser</LABEL>
	<LABEL name="EntityID">Entity</LABEL>
	<LABEL name="ItemID">Item</LABEL>
	<LABEL name="ShortcutName">Name</LABEL>
	<LABEL name="URL">URL</LABEL>
	<LABEL name="IsPinned">This Item is pinned to the top of the list.</LABEL>
	<LABEL name="IsPopup">Popup</LABEL>
	<LABEL name="IsPinnedTrue">Yes</LABEL>
	<LABEL name="IsPinnedFalse">No</LABEL>
	<LABEL name="IsPopupTrue">IsPopupTrue</LABEL>
	<LABEL name="IsPopupFalse">IsPopupFalse</LABEL>
	<LABEL name="NoUser">Not Logged On!</LABEL>
	<LABEL name="AddShortcutText">Shortcut Created Successfully!</LABEL>
	<LABEL name="Unpin">Unpin</LABEL>
	<LABEL name="Pin">Pin</LABEL>
	<LABEL name="Edit">Edit</LABEL>
	<LABEL name="Remove">Remove</LABEL>
	<LABEL name="ShortcutsText">Click the Shortcut name to go directly to it. Click the "Edit" link to modify the item properties. New Shortcuts can be created by clicking the Shortcut icon on the item detail page.</LABEL>
</LANGUAGE>
